nbproject_test/__init__.py
nbproject_test/_core.py
nbproject_test-0.6.0.dist-info/LICENSE
nbproject_test-0.6.0.dist-info/WHEEL
nbproject_test-0.6.0.dist-info/METADATA
nbproject_test-0.6.0.dist-info/RECORD
