Metadata-Version: 2.3
Name: nbproject_test
Version: 0.6.0
Summary: Testing for nbproject.
Author-email: Lamin Labs <laminlabs@gmail.com>
Requires-Dist: nbclient
Requires-Dist: nbformat
Requires-Dist: ipykernel
Requires-Dist: natsort
Requires-Dist: pre-commit ; extra == "dev"
Requires-Dist: nox ; extra == "dev"
Requires-Dist: pytest>=6.0 ; extra == "test"
Requires-Dist: pytest-cov ; extra == "test"
Project-URL: Home, https://github.com/laminlabs/nbproject-test
Provides-Extra: dev
Provides-Extra: test
